{
  "metadata": {
    "url": "https://www.logammulia.com/id/harga-emas-hari-ini",
    "source": "Antam Logam Mulia",
    "technique_used": "Network Capture + DOM Extraction",
    "scrape_date": "2026-04-24T20:45:54.210942"
  },
  "data": {
    "technique": "network_capture",
    "captured_apis": {
      "https://www.logammulia.com/cdn-cgi/speculation": {
        "prefetch": [
          {
            "eagerness": "conservative",
            "source": "document",
            "where": {
              "and": [
                {
                  "href_matches": "/*",
                  "relative_to": "document"
                }
              ]
            }
          }
        ]
      }
    },
    "api_count": 1,
    "tables": [
      {
        "title": "Harga Emas Hari Ini, 24 Apr 2026 - Emas Batangan",
        "headers": [
          "Berat",
          "Harga Dasar",
          "Harga (+Pajak PPh 0.25%)"
        ],
        "rows": [
          {
            "Berat": "0.5 gr",
            "Harga Dasar": "1,452,500",
            "Harga (+Pajak PPh 0.25%)": "1,456,131"
          },
          {
            "Berat": "1 gr",
            "Harga Dasar": "2,805,000",
            "Harga (+Pajak PPh 0.25%)": "2,812,013"
          },
          {
            "Berat": "2 gr",
            "Harga Dasar": "5,550,000",
            "Harga (+Pajak PPh 0.25%)": "5,563,875"
          },
          {
            "Berat": "3 gr",
            "Harga Dasar": "8,300,000",
            "Harga (+Pajak PPh 0.25%)": "8,320,750"
          },
          {
            "Berat": "5 gr",
            "Harga Dasar": "13,800,000",
            "Harga (+Pajak PPh 0.25%)": "13,834,500"
          },
          {
            "Berat": "10 gr",
            "Harga Dasar": "27,545,000",
            "Harga (+Pajak PPh 0.25%)": "27,613,863"
          },
          {
            "Berat": "25 gr",
            "Harga Dasar": "68,737,000",
            "Harga (+Pajak PPh 0.25%)": "68,908,843"
          },
          {
            "Berat": "50 gr",
            "Harga Dasar": "137,395,000",
            "Harga (+Pajak PPh 0.25%)": "137,738,488"
          },
          {
            "Berat": "100 gr",
            "Harga Dasar": "274,712,000",
            "Harga (+Pajak PPh 0.25%)": "275,398,780"
          },
          {
            "Berat": "250 gr",
            "Harga Dasar": "686,515,000",
            "Harga (+Pajak PPh 0.25%)": "688,231,288"
          },
          {
            "Berat": "500 gr",
            "Harga Dasar": "1,372,820,000",
            "Harga (+Pajak PPh 0.25%)": "1,376,252,050"
          },
          {
            "Berat": "1000 gr",
            "Harga Dasar": "2,745,600,000",
            "Harga (+Pajak PPh 0.25%)": "2,752,464,000"
          }
        ]
      },
      {
        "title": "Harga Emas Hari Ini, 24 Apr 2026 - Emas Batangan Gift Series",
        "headers": [
          "Berat",
          "Harga Dasar",
          "Harga (+Pajak PPh 0.25%)"
        ],
        "rows": [
          {
            "Berat": "0.5 gr",
            "Harga Dasar": "1,522,500",
            "Harga (+Pajak PPh 0.25%)": "1,526,306"
          },
          {
            "Berat": "1 gr",
            "Harga Dasar": "2,955,000",
            "Harga (+Pajak PPh 0.25%)": "2,962,388"
          }
        ]
      },
      {
        "title": "Harga Emas Hari Ini, 24 Apr 2026 - Emas Batangan Selamat Idul Fitri",
        "headers": [
          "Berat",
          "Harga Dasar",
          "Harga (+Pajak PPh 0.25%)"
        ],
        "rows": [
          {
            "Berat": "5 gr",
            "Harga Dasar": "14,773,000",
            "Harga (+Pajak PPh 0.25%)": "14,809,933"
          }
        ]
      },
      {
        "title": "Harga Emas Hari Ini, 24 Apr 2026 - Emas Batangan Imlek",
        "headers": [
          "Berat",
          "Harga Dasar",
          "Harga (+Pajak PPh 0.25%)"
        ],
        "rows": [
          {
            "Berat": "8 gr",
            "Harga Dasar": "23,294,800",
            "Harga (+Pajak PPh 0.25%)": "23,353,037"
          },
          {
            "Berat": "88 gr",
            "Harga Dasar": "253,537,600",
            "Harga (+Pajak PPh 0.25%)": "254,171,444"
          }
        ]
      },
      {
        "title": "Harga Emas Hari Ini, 24 Apr 2026 - Emas Batangan Batik Seri III",
        "headers": [
          "Berat",
          "Harga Dasar",
          "Harga (+Pajak PPh 0.25%)"
        ],
        "rows": [
          {
            "Berat": "10 gr",
            "Harga Dasar": "28,550,000",
            "Harga (+Pajak PPh 0.25%)": "28,621,375"
          },
          {
            "Berat": "20 gr",
            "Harga Dasar": "56,300,000",
            "Harga (+Pajak PPh 0.25%)": "56,440,750"
          }
        ]
      },
      {
        "title": "Harga Emas Hari Ini, 24 Apr 2026 - Perak Murni",
        "headers": [
          "Berat",
          "Harga Dasar",
          "Harga Sudah Termasuk PPN 11%"
        ],
        "rows": [
          {
            "Berat": "250 gr",
            "Harga Dasar": "12,475,000",
            "Harga Sudah Termasuk PPN 11%": "13,847,250"
          },
          {
            "Berat": "500 gr",
            "Harga Dasar": "24,150,000",
            "Harga Sudah Termasuk PPN 11%": "26,806,500"
          }
        ]
      },
      {
        "title": "Harga Emas Hari Ini, 24 Apr 2026 - Perak Heritage",
        "headers": [
          "Berat",
          "Harga Dasar",
          "Harga Sudah Termasuk PPN 11%"
        ],
        "rows": [
          {
            "Berat": "31.1 gr",
            "Harga Dasar": "2,049,932",
            "Harga Sudah Termasuk PPN 11%": "2,275,425"
          },
          {
            "Berat": "186.6 gr",
            "Harga Dasar": "11,178,076",
            "Harga Sudah Termasuk PPN 11%": "12,407,664"
          }
        ]
      },
      {
        "title": "Liontin Batik Seri III",
        "headers": [
          "Berat",
          "Harga Dasar",
          "Harga Sudah Termasuk PPN 1.65%",
          "Harga Sudah Termasuk PPN 1.1% + PPh 22 0.25%"
        ],
        "rows": [
          {
            "Berat": "8 gr",
            "Harga Dasar": "17,275,456",
            "Harga Sudah Termasuk PPN 1.65%": "17,560,501",
            "Harga Sudah Termasuk PPN 1.1% + PPh 22 0.25%": "17,508,675"
          }
        ]
      }
    ],
    "articles": [
      {
        "judul": "Verifikasi Produk",
        "url": "https://www.logammulia.com/product-verify",
        "thumbnail": "",
        "waktu": ""
      },
      {
        "judul": "Bahasa Indonesia",
        "url": "https://www.logammulia.com/change-language/id",
        "thumbnail": "https://www.logammulia.com/uploads/ngc_languages/5b3dc20ea0e2a_20180705140030-1.png",
        "waktu": ""
      },
      {
        "judul": "Emas Idul Fitri",
        "url": "https://www.logammulia.com/purchase/emas-idul-fitri",
        "thumbnail": "",
        "waktu": ""
      },
      {
        "judul": "Emas Batangan Batik",
        "url": "https://www.logammulia.com/purchase/seri-batik-indonesia",
        "thumbnail": "",
        "waktu": ""
      },
      {
        "judul": "Emas Idul Fitri",
        "url": "https://www.logammulia.com/product-list/emas-idul-fitri",
        "thumbnail": "",
        "waktu": ""
      },
      {
        "judul": "Perak Indonesian Heritage",
        "url": "https://www.logammulia.com/product-list/silverheritage",
        "thumbnail": "",
        "waktu": ""
      },
      {
        "judul": "Produk Industri",
        "url": "https://www.logammulia.com/product-list/produk-industri",
        "thumbnail": "",
        "waktu": ""
      },
      {
        "judul": "Perak Murni 99.95%",
        "url": "https://www.logammulia.com/product-list/perak",
        "thumbnail": "",
        "waktu": ""
      },
      {
        "judul": "View All Category",
        "url": "https://www.logammulia.com/product-list",
        "thumbnail": "",
        "waktu": ""
      },
      {
        "judul": "Harga Emas Hari Ini",
        "url": "https://www.logammulia.com/harga-emas-hari-ini",
        "thumbnail": "",
        "waktu": ""
      },
      {
        "judul": "Grafik Harga Emas",
        "url": "https://www.logammulia.com/grafik-harga-emas",
        "thumbnail": "",
        "waktu": ""
      },
      {
        "judul": "Cek Alamat Butik",
        "url": "https://www.logammulia.com/contact#butik-lm",
        "thumbnail": "",
        "waktu": ""
      },
      {
        "judul": "SIMULASI BUYBACK",
        "url": "https://www.logammulia.com/sell/gold",
        "thumbnail": "",
        "waktu": ""
      },
      {
        "judul": "Teknologi CertiEye",
        "url": "https://www.logammulia.com/id/harga-emas-hari-ini",
        "thumbnail": "",
        "waktu": ""
      },
      {
        "judul": "delivery.logammulia@antam.com",
        "url": "mailto:delivery.logammulia@antam.com",
        "thumbnail": "",
        "waktu": ""
      },
      {
        "judul": "Pengujian dan Analisis",
        "url": "https://www.logammulia.com/assaying-analysis",
        "thumbnail": "",
        "waktu": ""
      },
      {
        "judul": "Profil Logam Mulia",
        "url": "https://www.logammulia.com/about",
        "thumbnail": "",
        "waktu": ""
      },
      {
        "judul": "Berita dan Promo",
        "url": "https://www.logammulia.com/news",
        "thumbnail": "",
        "waktu": ""
      },
      {
        "judul": "Syarat dan Ketentuan",
        "url": "https://www.logammulia.com/pages/term-and-conditions",
        "thumbnail": "",
        "waktu": ""
      },
      {
        "judul": "Kebijakan Privasi",
        "url": "https://www.logammulia.com/pages/privacy-policy",
        "thumbnail": "",
        "waktu": ""
      }
    ]
  }
}