{
  "metadata": {
    "url": "https://www.logammulia.com/id/harga-emas-hari-ini",
    "source": "Antam Logam Mulia",
    "technique_used": "Direct Request",
    "scrape_date": "2026-03-31T00:01:46.389314"
  },
  "data": {
    "technique": "direct_request",
    "tables": [
      {
        "title": "Harga Emas Hari Ini, 30 Mar 2026 - Emas Batangan",
        "headers": [
          "Berat",
          "Harga Dasar",
          "Harga (+Pajak PPh 0.25%)"
        ],
        "rows": [
          {
            "Berat": "0.5 gr",
            "Harga Dasar": "1,468,500",
            "Harga (+Pajak PPh 0.25%)": "1,472,171"
          },
          {
            "Berat": "1 gr",
            "Harga Dasar": "2,837,000",
            "Harga (+Pajak PPh 0.25%)": "2,844,093"
          },
          {
            "Berat": "2 gr",
            "Harga Dasar": "5,614,000",
            "Harga (+Pajak PPh 0.25%)": "5,628,035"
          },
          {
            "Berat": "3 gr",
            "Harga Dasar": "8,396,000",
            "Harga (+Pajak PPh 0.25%)": "8,416,990"
          },
          {
            "Berat": "5 gr",
            "Harga Dasar": "13,960,000",
            "Harga (+Pajak PPh 0.25%)": "13,994,900"
          },
          {
            "Berat": "10 gr",
            "Harga Dasar": "27,865,000",
            "Harga (+Pajak PPh 0.25%)": "27,934,663"
          },
          {
            "Berat": "25 gr",
            "Harga Dasar": "69,537,000",
            "Harga (+Pajak PPh 0.25%)": "69,710,843"
          },
          {
            "Berat": "50 gr",
            "Harga Dasar": "138,995,000",
            "Harga (+Pajak PPh 0.25%)": "139,342,488"
          },
          {
            "Berat": "100 gr",
            "Harga Dasar": "277,912,000",
            "Harga (+Pajak PPh 0.25%)": "278,606,780"
          },
          {
            "Berat": "250 gr",
            "Harga Dasar": "694,515,000",
            "Harga (+Pajak PPh 0.25%)": "696,251,288"
          },
          {
            "Berat": "500 gr",
            "Harga Dasar": "1,388,820,000",
            "Harga (+Pajak PPh 0.25%)": "1,392,292,050"
          },
          {
            "Berat": "1000 gr",
            "Harga Dasar": "2,777,600,000",
            "Harga (+Pajak PPh 0.25%)": "2,784,544,000"
          }
        ]
      },
      {
        "title": "Harga Emas Hari Ini, 30 Mar 2026 - Emas Batangan Gift Series",
        "headers": [
          "Berat",
          "Harga Dasar",
          "Harga (+Pajak PPh 0.25%)"
        ],
        "rows": [
          {
            "Berat": "0.5 gr",
            "Harga Dasar": "1,538,500",
            "Harga (+Pajak PPh 0.25%)": "1,542,346"
          },
          {
            "Berat": "1 gr",
            "Harga Dasar": "2,987,000",
            "Harga (+Pajak PPh 0.25%)": "2,994,468"
          }
        ]
      },
      {
        "title": "Harga Emas Hari Ini, 30 Mar 2026 - Emas Batangan Selamat Idul Fitri",
        "headers": [
          "Berat",
          "Harga Dasar",
          "Harga (+Pajak PPh 0.25%)"
        ],
        "rows": [
          {
            "Berat": "5 gr",
            "Harga Dasar": "14,933,000",
            "Harga (+Pajak PPh 0.25%)": "14,970,333"
          }
        ]
      },
      {
        "title": "Harga Emas Hari Ini, 30 Mar 2026 - Emas Batangan Imlek",
        "headers": [
          "Berat",
          "Harga Dasar",
          "Harga (+Pajak PPh 0.25%)"
        ],
        "rows": [
          {
            "Berat": "8 gr",
            "Harga Dasar": "23,550,800",
            "Harga (+Pajak PPh 0.25%)": "23,609,677"
          },
          {
            "Berat": "88 gr",
            "Harga Dasar": "256,353,600",
            "Harga (+Pajak PPh 0.25%)": "256,994,484"
          }
        ]
      },
      {
        "title": "Harga Emas Hari Ini, 30 Mar 2026 - Emas Batangan Batik Seri III",
        "headers": [
          "Berat",
          "Harga Dasar",
          "Harga (+Pajak PPh 0.25%)"
        ],
        "rows": [
          {
            "Berat": "10 gr",
            "Harga Dasar": "28,870,000",
            "Harga (+Pajak PPh 0.25%)": "28,942,175"
          },
          {
            "Berat": "20 gr",
            "Harga Dasar": "56,940,000",
            "Harga (+Pajak PPh 0.25%)": "57,082,350"
          }
        ]
      },
      {
        "title": "Perak Murni",
        "headers": [
          "Berat",
          "Harga Dasar",
          "Harga Sudah Termasuk PPN 11%"
        ],
        "rows": [
          {
            "Berat": "250 gr",
            "Harga Dasar": "11,675,000",
            "Harga Sudah Termasuk PPN 11%": "12,959,250"
          },
          {
            "Berat": "500 gr",
            "Harga Dasar": "22,550,000",
            "Harga Sudah Termasuk PPN 11%": "25,030,500"
          }
        ]
      },
      {
        "title": "Perak Heritage",
        "headers": [
          "Berat",
          "Harga Dasar",
          "Harga Sudah Termasuk PPN 11%"
        ],
        "rows": [
          {
            "Berat": "31.1 gr",
            "Harga Dasar": "1,950,403",
            "Harga Sudah Termasuk PPN 11%": "2,164,947"
          },
          {
            "Berat": "186.6 gr",
            "Harga Dasar": "10,580,956",
            "Harga Sudah Termasuk PPN 11%": "11,744,861"
          }
        ]
      },
      {
        "title": "Liontin Batik Seri III",
        "headers": [
          "Berat",
          "Harga Dasar",
          "Harga Sudah Termasuk PPN 1.65%",
          "Harga Sudah Termasuk PPN 1.1% + PPh 22 0.25%"
        ],
        "rows": [
          {
            "Berat": "8 gr",
            "Harga Dasar": "17,275,456",
            "Harga Sudah Termasuk PPN 1.65%": "17,560,501",
            "Harga Sudah Termasuk PPN 1.1% + PPh 22 0.25%": "17,508,675"
          }
        ]
      }
    ],
    "inline_json": []
  }
}